{"name":"Battleship\u00ae Game","category":["Games "," Board Games "," Classic Board Games"],"image_src":["https:\/\/img.ssww.com\/cs_srgb\/q_90\/w_312\/v1551822812\/38\/57\/SWW13857.jpg","https:\/\/img.ssww.com\/cs_srgb\/q_90\/w_45\/v1551822813\/57\/01\/SWW1385701.jpg","https:\/\/img.ssww.com\/cs_srgb\/q_90\/w_45\/v1551822814\/57\/02\/SWW1385702.jpg"],"price_default":"$25.84","price_discount":"$21.99","sku":"#W13857","discription":"The classic combat and strategy game!\n\n\n\nHunt down, launch, and destroy your opponent\u2019s ships while hiding and protecting your own Each player\u2019s fleet includes a sub, patrol boat, destroyer, aircraft carrier, and fierce battleship Includes 10 plastic ships, 84 red \u201chit\u201d pegs, 168 white \u201cmiss\u201d pegs, label sheet, and instructions Game comes packed in 2 portable battle cases","stock":"InStock","brand":"Hasbro"}